floscraper/__init__.py
floscraper/cache.py
floscraper/default_user_agents.py
floscraper/models.py
floscraper/webscraper.py
floscraper-0.3.1.dist-info/AUTHORS.rst
floscraper-0.3.1.dist-info/LICENSE
floscraper-0.3.1.dist-info/METADATA
floscraper-0.3.1.dist-info/WHEEL
floscraper-0.3.1.dist-info/top_level.txt
floscraper-0.3.1.dist-info/RECORD
