Metadata-Version: 2.1
Name: floscraper
Version: 0.3.1
Summary: Simple webscraper built on top of requests and beautifulsoup
Home-page: https://github.com/the01/python-floscraper
Author: the01
Author-email: jungflor@gmail.com
License: MIT License
Keywords: floscrapper scraping web cache requests beautifulsoup
Platform: UNKNOWN
Classifier: Development Status :: 4 - Beta
Classifier: Intended Audience :: Developers
Classifier: License :: OSI Approved :: MIT License
Classifier: Natural Language :: English
Classifier: Programming Language :: Python :: 2
Classifier: Programming Language :: Python :: 2.7
Requires-Dist: flotils (<0.6,>=0.5)
Requires-Dist: beautifulsoup4 (<4.9,>=4.6.0)
Requires-Dist: portalocker (<1.6,>=0.5.5)
Requires-Dist: requests (<3.0,>=2.18.4)
Requires-Dist: html2text (>=2017.10.4)
